PyGWP/__init__.py
PyGWP/core.py
PyGWP/tools.py
PyGWP/test/__init__.py
PyGWP/test/core.py
PyGWP-0.0.32.dist-info/LICENSE
PyGWP-0.0.32.dist-info/METADATA
PyGWP-0.0.32.dist-info/WHEEL
PyGWP-0.0.32.dist-info/top_level.txt
PyGWP-0.0.32.dist-info/RECORD
