Metadata-Version: 2.1
Name: PyGWP
Version: 0.0.32
Summary: A CO2-equivalent computer based on static or dynamic CO2-relative global warming potentials coded in Python27, PyGWP.
Home-page: https://github.com/lfaucheux/PyGWP
Author: Laurent Faucheux
Author-email: laurent.faucheux@hotmail.fr
License: MIT
Download-URL: https://github.com/lfaucheux/PyGWP/archive/0.0.32.tar.gz
Keywords: Global Warming Potential,Static Global Warming Potential,Dynamic Global Warming Potential
Platform: UNKNOWN
Classifier: Programming Language :: Python :: 2.7
Classifier: Intended Audience :: Developers
Classifier: Intended Audience :: Science/Research
Classifier: Topic :: Scientific/Engineering
Requires-Dist: numpy
